README
setup.py
sip_tpv/__init__.py
sip_tpv/pv_to_sip.py
sip_tpv/pvsiputils.py
sip_tpv/reverse.py
sip_tpv/sip_to_pv.py
sip_tpv.egg-info/PKG-INFO
sip_tpv.egg-info/SOURCES.txt
sip_tpv.egg-info/dependency_links.txt
sip_tpv.egg-info/requires.txt
sip_tpv.egg-info/top_level.txt