Metadata-Version: 1.1
Name: sip-tpv
Version: 1.1
Summary: Conversion of distortion representations in FITS headers between SIP and TPV formats.
Home-page: https://github.com/stargaser/sip_tpv
Author: David Shupe
Author-email: shupe@ipac.caltech.edu
License: BSD
Platform: UNKNOWN
Classifier: Intended Audience :: Science/Research
Classifier: Topic :: Scientific/Engineering :: Astronomy
Classifier: License :: OSI Approved :: BSD License
Classifier: Programming Language :: Python
